CHANGELOG.txt
LICENCE.txt
MANIFEST.in
README.txt
setup.py
calc_v1.egg-info/PKG-INFO
calc_v1.egg-info/SOURCES.txt
calc_v1.egg-info/dependency_links.txt
calc_v1.egg-info/top_level.txt
compute/__init__.py
compute/add_number.py
compute/div_number.py
compute/mul_number.py
compute/sub_number.py