Metadata-Version: 2.1
Name: calc-v1
Version: 0.0.1
Summary: Trial Basic calculator library, individual functions
Home-page: 
Author: Movin Fernandes
Author-email: movin.fernandes@hotmail.com
License: MIT
Keywords: basic,calculator
License-File: LICENCE.txt
